views_storage/__init__.py
views_storage/backends/__init__.py
views_storage/backends/azure.py
views_storage/backends/dictionary.py
views_storage/backends/local.py
views_storage/backends/sftp.py
views_storage/backends/sql.py
views_storage/backends/storage_backend.py
views_storage/key_value_store.py
views_storage/models.py
views_storage/serializers/__init__.py
views_storage/serializers/csv.py
views_storage/serializers/json.py
views_storage/serializers/parquet.py
views_storage/serializers/pickle.py
views_storage/serializers/serializer.py
views_storage/sftp_storage.py
views_storage/types.py
views_storage-1.1.7.dist-info/LICENSE
views_storage-1.1.7.dist-info/METADATA
views_storage-1.1.7.dist-info/WHEEL
views_storage-1.1.7.dist-info/RECORD
